tanuna/CT_LTI.py
tanuna/__init__.py
tanuna/root.py
tanuna/examples/__init__.py
tanuna/examples/laser.py
tanuna-0.1.dist-info/LICENSE
tanuna-0.1.dist-info/METADATA
tanuna-0.1.dist-info/WHEEL
tanuna-0.1.dist-info/top_level.txt
tanuna-0.1.dist-info/RECORD
