Metadata-Version: 2.1
Name: tanuna
Version: 0.1
Summary: Python tools to work with dynamic systems
Home-page: https://github.com/adrianschlatter/tanuna
Author: Adrian Schlatter
License: Revised BSD
Keywords: lti,continuous time,filter,state space,system,control,dynamic
Platform: UNKNOWN
Classifier: Development Status :: 3 - Alpha
Classifier: Intended Audience :: Education
Classifier: Intended Audience :: Science/Research
Classifier: Topic :: Utilities
Classifier: License :: OSI Approved :: BSD License
Classifier: Programming Language :: Python :: 3
Classifier: Operating System :: OS Independent
Requires-Python: <4,>=3.6
Requires-Dist: numpy
Requires-Dist: scipy
Provides-Extra: dev
Requires-Dist: check-manifest ; extra == 'dev'
Provides-Extra: test
Requires-Dist: pytest ; extra == 'test'
Requires-Dist: twine ; extra == 'test'
Requires-Dist: check-manifest ; extra == 'test'
Requires-Dist: readme-renderer ; extra == 'test'
Requires-Dist: flake8 ; extra == 'test'
Requires-Dist: coverage ; extra == 'test'
